advanced_captcha_lib/__init__.py
advanced_captcha_lib/core.py
advanced_captcha_lib/messages.py
advanced_captcha_lib/ui.py
advanced_captcha_lib/universal.py
advanced_captcha_lib/utils.py
advanced_captcha_lib-1.0.dist-info/METADATA
advanced_captcha_lib-1.0.dist-info/WHEEL
advanced_captcha_lib-1.0.dist-info/top_level.txt
advanced_captcha_lib-1.0.dist-info/RECORD
