Metadata-Version: 2.4
Name: advanced_captcha_lib
Version: 1.0
Summary: Advanced CAPTCHA library with language detection
Author: TuFueguito
Requires-Python: >=3.9
Requires-Dist: PySide6
Requires-Dist: customtkinter
Requires-Dist: PyQt5
Requires-Dist: PyQt6
Requires-Dist: wxPython
Dynamic: author
Dynamic: requires-dist
Dynamic: requires-python
Dynamic: summary
